encoder8to3/encoder_8to3.v
module encoder_8to3 (
    input [7:0] in,      
    output reg [2:0] out  
);

always @(*) begin
    casex (in)
        8'b1xxxxxxx: out = 3'b111; 
        8'b01xxxxxx: out = 3'b110;
        8'b001xxxxx: out = 3'b101;
        8'b0001xxxx: out = 3'b100;
        8'b00001xxx: out = 3'b011;
        8'b000001xx: out = 3'b010;
        8'b0000001x: out = 3'b001;
        8'b00000001: out = 3'b000; 
        default: out = 3'b000;     
    endcase
end
endmodule

encoder8to3/encoder_8to3_tb.v
`timescale 1ns/1ps
module encoder_8to3_tb();
    reg [7:0] in;
    wire [2:0] out;
    
    encoder_8to3 inst (
	 .in(in), 
	 .out(out)
	 );
    
    initial begin
        $dumpfile("encoder_wave.vcd");
        $dumpvars(0, encoder_8to3_tb);
        
        #10 in = 8'b00000001; 
        #10 in = 8'b00000010; 
        #10 in = 8'b00000100; 
        #10 in = 8'b00001000; 
        #10 in = 8'b00010000; 
        #10 in = 8'b00100000;
        #10 in = 8'b01000000; 
        #10 in = 8'b10000000; 
        
    
        #10 in = 8'b00010010; 
        #10 in = 8'b00100100; 
        #10 in = 8'b11000000; 
        
        $finish;
    end
endmodule

encoder8to3/simulation/modelsim/encoder_wave.vcd
$date
	Fri Mar 28 23:13:10 2025
$end
$version
	ModelSim Version 2020.1
$end
$timescale
	1ps
$end

$scope module encoder_8to3_tb $end
$var reg 8 ! in [7:0] $end
$var wire 1 " out [2] $end
$var wire 1 # out [1] $end
$var wire 1 $ out [0] $end

$scope module dut $end
$var wire 1 % in [7] $end
$var wire 1 & in [6] $end
$var wire 1 ' in [5] $end
$var wire 1 ( in [4] $end
$var wire 1 ) in [3] $end
$var wire 1 * in [2] $end
$var wire 1 + in [1] $end
$var wire 1 , in [0] $end
$var reg 3 - out [2:0] $end
$upscope $end
$upscope $end
$enddefinitions $end
#0
$dumpvars
bx !
bx -
x$
x#
x"
x,
x+
x*
x)
x(
x'
x&
x%
$end
#10000
b1 !
1,
0+
0*
0)
0(
0'
0&
0%
b0 -
0$
0#
0"
#20000
b10 !
0,
1+
b1 -
1$
#30000
b100 !
0+
1*
b10 -
0$
1#
#40000
b1000 !
0*
1)
b11 -
1$
#50000
b10000 !
0)
1(
b100 -
0$
0#
1"
#60000
b100000 !
0(
1'
b101 -
1$
#70000
b1000000 !
0'
1&
b110 -
0$
1#
#80000
b10000000 !
0&
1%
b111 -
1$
#90000
b10010 !
1+
1(
0%
b100 -
0$
0#
#100000
b100100 !
0+
1*
0(
1'
b101 -
1$
#110000
b11000000 !
