dffdifferent/dff_behavioral.v
module dff_behavioral(
    input clk,
    input rst_async,
    input rst_sync,
    input D,
    output reg Q
);

always @(posedge clk or posedge rst_async) begin
    if (rst_async) 
        Q <= 1'b0;
    else if (rst_sync) 
        Q <= 1'b0;
    else 
        Q <= D;
end

endmodule

dffdifferent/dff_structural.v
module dff_structural(
    input clk,
    input rst_async,
    input rst_sync,
    input D,
    output Q
);


wire nand1_out, nand2_out;
wire master_out, master_feedback;


wire nand3_out, nand4_out;
wire slave_out, slave_feedback;


nand nand1(nand1_out, D, clk);
nand nand2(nand2_out, ~D, clk);
nand nand3(master_out, nand1_out, master_feedback);
nand nand4(master_feedback, nand2_out, master_out);


nand nand5(nand3_out, master_out, ~clk);
nand nand6(nand4_out, ~master_out, ~clk);
nand nand7(slave_out, nand3_out, slave_feedback);
nand nand8(slave_feedback, nand4_out, slave_out);

assign Q = rst_async ? 1'b0 : 
           (rst_sync & clk) ? 1'b0 : slave_out;

endmodule

dffdifferent/dff_tb.v
`timescale 1ns/1ps
module dff_tb();

reg clk, rst_async, rst_sync, D;
wire Q_structural, Q_behavioral;

dff_structural structural_dff (
    .clk(clk),
    .rst_async(rst_async),
    .rst_sync(rst_sync),
    .D(D),
    .Q(Q_structural)
);

dff_behavioral behavioral_dff (
    .clk(clk),
    .rst_async(rst_async),
    .rst_sync(rst_sync),
    .D(D),
    .Q(Q_behavioral)
);


initial begin
    clk = 0;
    repeat (20) #5 clk = ~clk; 
end

initial begin
    
    rst_async = 1; rst_sync = 0; D = 0;
    #20 rst_async = 0;
    
   
    D = 1; #20;        
    rst_sync = 1; #20;   
    rst_sync = 0; D = 0; #20;
    D = 1; #20;
    rst_async = 1; #20;  
    rst_async = 0; #40;
    
    $finish;
end

initial begin
    $dumpfile("dff_waves.vcd");
    $dumpvars(0, dff_tb);
end

endmodule

dffdifferent/simulation/modelsim/dff_waves.vcd
$date
	Fri Apr 04 23:29:12 2025
$end
$version
	ModelSim Version 2020.1
$end
$timescale
	1ps
$end

$scope module dff_tb $end
$var reg 1 ! clk $end
$var reg 1 " rst_async $end
$var reg 1 # rst_sync $end
$var reg 1 $ D $end
$var wire 1 % Q_structural $end
$var wire 1 & Q_behavioral $end

$scope module structural_dff $end
$var wire 1 ' clk $end
$var wire 1 ( rst_async $end
$var wire 1 ) rst_sync $end
$var wire 1 * D $end
$var wire 1 % Q $end
$var wire 1 + nand1_out $end
$var wire 1 , nand2_out $end
$var wire 1 - master_out $end
$var wire 1 . master_feedback $end
$var wire 1 / nand3_out $end
$var wire 1 0 nand4_out $end
$var wire 1 1 slave_out $end
$var wire 1 2 slave_feedback $end
$upscope $end

$scope module behavioral_dff $end
$var wire 1 3 clk $end
$var wire 1 4 rst_async $end
$var wire 1 5 rst_sync $end
$var wire 1 6 D $end
$var reg 1 7 Q $end
$upscope $end
$upscope $end
$enddefinitions $end
#0
$dumpvars
0!
1"
0#
0$
07
0%
0&
1+
1,
x-
x.
x/
x0
x1
x2
06
05
14
03
0*
0)
1(
0'
$end
#5000
1!
1'
0,
10
1/
1.
0-
13
#10000
0!
0'
1,
00
12
01
03
#15000
1!
1'
0,
10
13
#20000
0"
1$
0!
0(
1*
16
0'
1,
00
04
03
#25000
1!
1'
0+
10
1-
0.
13
17
1&
#30000
0!
0'
1+
0/
11
1%
02
03
#35000
1!
1'
0+
1/
13
#40000
1#
0!
1)
15
0'
1+
0/
03
#45000
1!
1'
0%
0+
1/
13
07
0&
#50000
0!
0'
1%
1+
0/
03
#55000
1!
1'
0%
0+
1/
13
#60000
0#
0$
0!
0)
05
0*
06
0'
1%
1+
0/
03
#65000
1!
1'
0,
1/
1.
0-
13
#70000
0!
0'
1,
00
12
01
0%
03
#75000
1!
1'
0,
10
13
#80000
1$
0!
1*
16
0'
1,
00
03
#85000
1!
1'
0+
10
1-
0.
13
17
1&
#90000
0!
0'
1+
0/
11
1%
02
03
#95000
1!
1'
0+
1/
13
#100000
1"
0!
1(
0'
0%
1+
0/
14
03
07
0&
#120000
0"
0(
1%
04
