jkflipflop/jk_flipflop.v
module jk_flipflop(
    input clk,
    input clear_n,    
    input preset_n,   
    input J,
    input K,
    output reg Q,
    output reg Q_n     
);

always @(posedge clk or negedge clear_n or negedge preset_n) begin
    if (!clear_n) begin    
        Q <= 1'b0;
        Q_n <= 1'b1;
    end
    else if (!preset_n) begin 
        Q <= 1'b1;
        Q_n <= 1'b0;
    end
    else begin               
        case ({J,K})
            2'b00: Q <= Q;     
            2'b01: Q <= 1'b0; 
            2'b10: Q <= 1'b1;  
            2'b11: Q <= ~Q;    
        endcase
        Q_n <= ~Q;           
    end
end

endmodule

jkflipflop/jk_flipflop_tb.v
`timescale 1ns/1ps
module jk_flipflop_tb();

reg clk, clear_n, preset_n, J, K;
wire Q, Q_n;


jk_flipflop dut (
    .clk(clk),
    .clear_n(clear_n),
    .preset_n(preset_n),
    .J(J),
    .K(K),
    .Q(Q),
    .Q_n(Q_n)
);


initial begin
    clk = 0;
    repeat (20) #5 clk = ~clk;
end


initial begin
   
    clear_n = 1; preset_n = 1; J = 0; K = 0;
  
    #10 clear_n = 0; 
    #10 clear_n = 1;  
    
   
    #10 preset_n = 0; 
    #10 preset_n = 1;
    
  
    #10 J = 0; K = 0; 
    #10 J = 0; K = 1;
    #10 J = 1; K = 0;
    #10 J = 1; K = 1; 
    #30;
    
   
    #10 clear_n = 0;
    #10 clear_n = 1;
    
   
    #10 preset_n = 0;
    #10 preset_n = 1;
    
    #20 $finish;
end


initial begin
    $dumpfile("jk_ff_waves.vcd");
    $dumpvars(0, jk_flipflop_tb);
    $display("Time\tClk\tClear\tPreset\tJ\tK\tQ\tQ_n");
    $monitor("%0t\t%b\t%b\t%b\t%b\t%b\t%b\t%b", 
            $time, clk, clear_n, preset_n, J, K, Q, Q_n);
end

endmodule

jkflipflop/simulation/modelsim/jk_ff_waves.vcd
$date
	Fri Apr 04 23:37:19 2025
$end
$version
	ModelSim Version 2020.1
$end
$timescale
	1ps
$end

$scope module jk_flipflop_tb $end
$var reg 1 ! clk $end
$var reg 1 " clear_n $end
$var reg 1 # preset_n $end
$var reg 1 $ J $end
$var reg 1 % K $end
$var wire 1 & Q $end
$var wire 1 ' Q_n $end

$scope module dut $end
$var wire 1 ( clk $end
$var wire 1 ) clear_n $end
$var wire 1 * preset_n $end
$var wire 1 + J $end
$var wire 1 , K $end
$var reg 1 - Q $end
$var reg 1 . Q_n $end
$upscope $end
$upscope $end
$enddefinitions $end
#0
$dumpvars
0!
1"
1#
0$
0%
x-
x.
x&
x'
0,
0+
1*
1)
0(
$end
#5000
1!
1(
#10000
0"
0!
0)
0(
0-
1.
0&
1'
#15000
1!
1(
#20000
1"
0!
1)
0(
#25000
1!
1(
#30000
0#
0!
0*
0(
1-
0.
1&
0'
#35000
1!
1(
#40000
1#
0!
1*
0(
#45000
1!
1(
#50000
0!
0(
#55000
1!
1(
#60000
1%
0!
1,
0(
#65000
1!
1(
0-
0&
#70000
1$
0%
0!
1+
0,
0(
#75000
1!
1(
1-
1.
1&
1'
#80000
1%
0!
1,
0(
#85000
1!
1(
0-
0.
0&
0'
#90000
0!
0(
#95000
1!
1(
1-
1.
1&
1'
#100000
0!
0(
#120000
0"
0)
0-
0&
#130000
1"
1)
#140000
0#
0*
1-
0.
1&
0'
