sequential_processor/d_flipflop.v
module d_flipflop (
    input wire clk,      //clock Signal
    input wire rst,      //asynchronous Reset
    input wire d,        //input
    output reg q         //output
);

always @(posedge clk or posedge rst) begin
    if (rst) 
        q <= 1'b0;       //reset output to 0
    else 
        q <= d;          //store input on rising edge of clock
end

endmodule

sequential_processor/tb_d_flipflop.v
`timescale 1ns / 1ps
module tb_d_flipflop();
reg clk;
reg rst;
reg d;
wire q;

d_flipflop inst (
    .clk(clk),
    .rst(rst),
    .d(d),
    .q(q)
);

//clock- 10ns period 100 MHz
always #5 clk = ~clk;

initial begin
    $dumpfile("tb_d_flipflop.vcd");
    $dumpvars(0, tb_d_flipflop);

    clk = 0;
    rst = 1; d = 0;  //active reset
    #10 rst = 0;     //deactivate reset
    d = 1; #10;      //input = 1
    d = 0; #10;      //input = 0
    d = 1; #10;      //input = 1
    rst = 1; #10;    //activate reset
    rst = 0; #10;    //deactivate reset

    #20 $finish;
end

endmodule

sequential_processor/simulation/modelsim/tb_d_flipflop.vcd
$date
	Wed Apr 09 21:17:38 2025
$end
$version
	ModelSim Version 2020.1
$end
$timescale
	1ps
$end

$scope module tb_d_flipflop $end
$var reg 1 ! clk $end
$var reg 1 " rst $end
$var reg 1 # d $end
$var wire 1 $ q $end

$scope module inst $end
$var wire 1 % clk $end
$var wire 1 & rst $end
$var wire 1 ' d $end
$var reg 1 ( q $end
$upscope $end
$upscope $end
$enddefinitions $end
#0
$dumpvars
0!
1"
0#
0(
0$
0'
1&
0%
$end
#5000
1!
1%
#10000
0"
1#
0!
1'
0&
0%
#15000
1!
1%
1(
1$
#20000
0#
0!
0'
0%
#25000
1!
1%
0(
0$
#30000
1#
0!
1'
0%
#35000
1!
1%
1(
1$
#40000
1"
0!
1&
0%
0(
0$
#45000
1!
1%
#50000
0"
0!
0&
0%
#55000
1!
1%
1(
1$
